Workbook

Sheet Executive Summary
A1: AMUSEMENT RIDE CRM & INVENTORY SYSTEM
A2: Technical Scope Work Estimation & Project Execution Metrics (.NET 8 Razor Pages)
B4: TOTAL PROJECT EFFORT | D4: CALENDAR DURATION | F4: CORE FEATURE MODULES | H4: SPECIALIST TEAM SIZE
B5: 1,088 Hours | D5: 13.6 Weeks (~3.5 Mo) | F5: 14 Modules | H5: 4 Resources
B8: 1. Effort Distribution by Engineering Discipline
B9: Discipline | C9: Effort (Hours) | D9: % of Total | E9: Primary Tech Stack / Tools | F9: Assigned Role
B10: Database Architecture & EF Core 8.0 | C10: ='Granular Breakdown'!D18 | D10: ='Granular Breakdown'!D18/'Granular Breakdown'!H18 | E10: SQL Server, EF Core 8.0, Migrations, RowVersion | F10: Lead Architect / Senior Backend
B11: Backend Business Logic, Services & Handlers | C11: ='Granular Breakdown'!E18 | D11: ='Granular Breakdown'!E18/'Granular Breakdown'!H18 | E11: C# 12, ASP.NET Core 8.0, QBWC SOAP, Polly | F11: Senior Full-Stack Developers (x2)
B12: Frontend UI, Razor Pages & Bootstrap 5.3 | C12: ='Granular Breakdown'!F18 | D12: ='Granular Breakdown'!F18/'Granular Breakdown'!H18 | E12: Razor Pages (.cshtml), Bootstrap 5.3, Bootstrap Icons | F12: Full-Stack / UI Developers
B13: Quality Assurance, Unit & E2E Integration Testing | C13: ='Granular Breakdown'!G18 | D13: ='Granular Breakdown'!G18/'Granular Breakdown'!H18 | E13: xUnit, Moq, Testcontainers, Selenium/Playwright | F13: QA Automation Engineer / Team
B14: Total Estimated Effort | C14: =SUM(C10:C13) | D14: =SUM(D10:D13) | E14: All Technical Layers | F14: 4 Core Team Members
B17: 2. Phased Milestone Execution Schedule
B18: Phase | C18: Milestone Focus | D18: Target Duration | E18: Total Hours | F18: % Total | G18: Key Deliverables
B19: Phase 1 | C19: Foundation, Master Data & Part Merging | D19: Weeks 1 - 3 | E19: 200 | F19: =D19/$D$25 | G19: Schema, Auth, Customers, Rides, Multi-Vendor Parts, Part Merge Tool
B20: Phase 2 | C20: Customer Quotes, Orders & Inventory Reservations | D20: Weeks 4 - 6 | E20: 244 | F20: =D20/$D$25 | G20: Quote workflow, Markup formula, Order lifecycle, Holding bin engine
B21: Phase 3 | C21: Purchasing Queue, POs, AI Invoices & Receiving | D21: Weeks 7 - 9 | E21: 336 | F21: =D21/$D$25 | G21: Demand consolidation, Vendor POs, Document AI review, ZPL label printing
B22: Phase 4 | C22: Shipping Management & UPS REST Integration | D22: Weeks 10 - 11 | E22: 88 | F22: =D22/$D$25 | G22: Complete/Partial shipping, Holding release, UPS live rating & label generation
B23: Phase 5 | C23: Customer Invoicing & QuickBooks Desktop Sync | D23: Weeks 12 - 13 | E23: 168 | F23: =D23/$D$25 | G23: Billing queue, QBWC SOAP Bridge, qbXML customer/invoice/bill sync
B24: Phase 6 | C24: End-to-End Hardening, User Acceptance & Launch | D24: Week 14 | E24: 52 | F24: =D24/$D$25 | G24: Full integrated scenario testing, Pilot data sync, Go-live deployment
B25: Total | C25: Complete Scope Delivery | D25: 14 Calendar Weeks | E25: =SUM(E19:E24) | F25: =SUM(F19:F24) | G25: Full Production Readiness

Sheet Granular Breakdown
A1: GRANULAR TASK & WORK ESTIMATION BREAKDOWN
A2: Detailed Breakdown by Feature Module, Technical Layer and Task Scope
A3: ID | B3: Feature Module | C3: Functional Scope & Deliverables | D3: DB / EF Core (Hrs) | E3: Backend Logic (Hrs) | F3: Frontend UI (Hrs) | G3: Testing & QA (Hrs) | H3: Total Module Hours
A4: MOD-01 | B4: 1. Foundation, Identity & Data Layer | C4: EF Core 8.0 schema, AuditableEntity base classes, Identity RBAC (Admin, Office, Buyer, Warehouse, Accounting), User management Razor Pages | D4: 18 | E4: 20 | F4: 14 | G4: 12 | H4: =SUM(D4:G4)
A5: MOD-02 | B5: 2. Customer & Ride Tracking | C5: Customer master (QB sync flag), Multi-contact management, Customer rides (Manufacturer, Model, Serial #), Ride selector component | D5: 8 | E5: 14 | F5: 16 | G5: 10 | H5: =SUM(D5:G5)
A6: MOD-03 | B6: 3. Inventory Master & Part Merge Tool | C6: Multi-vendor sources (EUR cost, lowest cost default), Ride applications, Non-stocked part flags, Duplicate part merge wizard with audit history | D6: 16 | E6: 28 | F6: 22 | G6: 18 | H6: =SUM(D6:G6)
A7: MOD-04 | B7: 4. Customer Quotes & Dynamic Pricing | C7: Configurable EUR factor & Markup, Quote creation, PDF terms generation, Expiration dates, 1-click conversion to Customer Order | D7: 10 | E7: 24 | F7: 20 | G7: 14 | H7: =SUM(D7:G7)
A8: MOD-05 | B8: 5. Customer Orders & Holding Bins | C8: Order workflow (Quote -> Shipped), Complete vs Partial shipment flags, Order holding location allocation, Manual price & charge adjustments | D8: 14 | E8: 32 | F8: 26 | G8: 20 | H8: =SUM(D8:G8)
A9: MOD-06 | B9: 6. Inventory Reservation Engine | C9: Real-time state machine: Available = QOH - Reserved, Optimistic concurrency (RowVersion), Atomic stock locking, Deficit routing to queue | D9: 12 | E9: 36 | F9: 12 | G9: 24 | H9: =SUM(D9:G9)
A10: MOD-07 | B10: 7. Purchasing Queue & Aggregation | C10: Demand aggregation from order deficits & ROP triggers, Consolidate by Vendor + Ride, Source order traceability, Manual qty adjustments | D10: 12 | E10: 34 | F10: 24 | G10: 18 | H10: =SUM(D10:G10)
A11: MOD-08 | B11: 8. Purchase Order Management | C11: PO generation in EUR, Ride/Serial display for vendor verification, PO editing post-dispatch, Order line purpose retention (demand vs stock) | D11: 10 | E11: 22 | F11: 20 | G11: 12 | H11: =SUM(D11:G11)
A12: MOD-09 | B12: 9. AI Vendor Invoice Processing | C12: Azure Document Intelligence / Vision API integration, Split-screen PDF extraction UI, Part cross-referencing, Master cost updates & open order alerts | D12: 10 | E12: 38 | F12: 32 | G12: 22 | H12: =SUM(D12:G12)
A13: MOD-10 | B13: 10. Warehouse Receiving & Labels | C13: PO line receiving, Partial receipt tracking, Over-delivery warning gates, Auto-reservation & holding directives, ZPL thermal barcode label printing | D13: 12 | E13: 28 | F13: 24 | G13: 18 | H13: =SUM(D13:G13)
A14: MOD-11 | B14: 11. Shipping & UPS REST API | C14: Complete vs Partial fulfillment dashboard, Pick lists from warehouse & holding bins, UPS REST API (Rating, Shipping labels, Tracking #), Manual override | D14: 10 | E14: 34 | F14: 24 | G14: 20 | H14: =SUM(D14:G14)
A15: MOD-12 | B15: 12. Customer Invoicing Queue | C15: Post-shipment billing queue, Multiple shipments -> multiple invoices, Additional charges (shipping, rush fee, discount), Manual review approval | D15: 8 | E15: 18 | F15: 16 | G15: 12 | H15: =SUM(D15:G15)
... A17: MOD-14 | B17: 14. Audit Trail, Dashboard & Settings | C17: Operational command center, Price change discrepancy alerts, Configuration page (EUR factor, markup), Complete transaction audit history | D17: 8 | E17: 18 | F17: 18 | G17: 12 | H17: =SUM(D17:G17)
A18: TOTAL | B18: All 14 Project Modules | C18: Complete ASP.NET Core 8.0 Razor Pages Execution | D18: =SUM(D4:D17) | E18: =SUM(E4:E17) | F18: =SUM(F4:F17) | G18: =SUM(G4:G17) | H18: =SUM(H4:H17)

Sheet Staffing & Schedule
A1: RESOURCE STAFFING PLAN & 14-WEEK ALLOCATION
A2: Weekly Capacity Allocation per Specialist Resource
A3: Resource Role | B3: Focus & Core Responsibilities | C3: Weekly Hours | D3: Total Hours | E3: Allocation % | F3: W1 | G3: W2 | H3: W3 | I3: W4 | J3: W5 | K3: W6 | L3: W7 | M3: W8 | N3: W9 | O3: W10 | P3: W11 | Q3: W12 | R3: W13 | S3: W14
A4: Lead Architect / Tech Lead | B4: Architecture, QBWC SOAP Bridge, Concurrency, Security, Code Reviews | C4: 18 | D4: =C4*14 | E4: 45% | F4: 18 | G4: 18 | H4: 18 | I4: 18 | J4: 18 | K4: 18 | L4: 18 | M4: 18 | N4: 18 | O4: 18 | P4: 18 | Q4: 18 | R4: 18 | S4: 18
A5: Senior Full-Stack Dev 1 | B5: EF Core Models, Reservation Engine, Orders, Purchasing Queue, Receiving | C5: 35 | D5: =C5*14 | E5: 87.5% | F5: 35 | G5: 35 | H5: 35 | I5: 35 | J5: 35 | K5: 35 | L5: 35 | M5: 35 | N5: 35 | O5: 35 | P5: 35 | Q5: 35 | R5: 35 | S5: 35
A6: Senior Full-Stack Dev 2 | B6: AI Document Extraction, Razor Pages UI, UPS API, Invoicing, Labels | C6: 35 | D6: =C6*14 | E6: 87.5% | F6: 35 | G6: 35 | H6: 35 | I6: 35 | J6: 35 | K6: 35 | L6: 35 | M6: 35 | N6: 35 | O6: 35 | P6: 35 | Q6: 35 | R6: 35 | S6: 35
A7: QA & Automation Engineer | B7: Test Plans, Integration Tests, QB Synchronization Verification, UAT | C7: 16 | D7: =C7*14 | E7: 40% | F7: 12 | G7: 12 | H7: 14 | I7: 14 | J7: 16 | K7: 16 | L7: 18 | M7: 18 | N7: 18 | O7: 18 | P7: 18 | Q7: 18 | R7: 20 | S7: 20
A8: TOTAL TEAM VELOCITY | B8: Blended Engineering Velocity (Hrs/Wk) | C8: =SUM(C4:C7) | D8: =SUM(D4:D7) | E8: 100% Blended | F8: =SUM(F4:F7) | G8: =SUM(G4:G7) | H8: =SUM(H4:H7) | I8: =SUM(I4:I7) | J8: =SUM(J4:J7) | K8: =SUM(K4:K7) | L8: =SUM(L4:L7) | M8: =SUM(M4:M7) | ... S8: =SUM(S4:S7)

Sheet Assumptions & Risks
A1: PROJECT ASSUMPTIONS & RISK MITIGATION REGISTER
A2: Technical Preconditions, External Constraints, and Risk Management
A4: 1. Technical & Architectural Assumptions
A5: ID | B5: Domain Area | C5: Assumption Description | D5: Impact if Invalidated
A6: ASM-01 | B6: QuickBooks Desktop | C6: Client operates a supported QuickBooks Desktop Enterprise / Premier version and provides a sanitized .QBW company file for local development & staging. | D6: High: Delays in sync development if QB Desktop instance cannot be tested locally.
A7: ASM-02 | B7: QBWC Integration Protocol | C7: Sync is implemented using the standard QuickBooks Web Connector (QBWC) SOAP protocol. PO sync is excluded from Phase 1 per scope §20. | D7: Medium: Custom Windows COM service would require additional development hours.
A8: ASM-03 | B8: Document AI Service | C8: Scanned vendor invoices are at least 200 DPI resolution, and client provisions an Azure Document Intelligence or OpenAI Vision API subscription. | D8: High: Poor OCR quality requires more manual human data entry.
A9: ASM-04 | B9: Zebra / Thermal Hardware | C9: Warehouse label printers support raw ZPL over TCP/IP (port 9100) or standard Windows network print spooling. | D9: Low: PDF fallback printing will be available through the browser.
A10: ASM-05 | B10: Pricing Formula & Currency | C10: Vendor invoices are in Euros (EUR). Master conversion factor and markup remain system-wide configurable. Inbound freight is not allocated to unit cost. | D10: Medium: Per-part freight allocation would require complex cost accounting adjustments.
A11: ASM-06 | B11: Out-of-Scope Confirmation | C11: CRM/ACT sync, AI photo part recognition, mobile Zebra handheld apps, and automatic email dispatch are confirmed as Phase 2 items (§25). | D11: High: Introducing mobile apps or CRM in Phase 1 would expand scope significantly.
A14: 2. Technical Risk Management Register
A15: Risk ID | B15: Risk Description | C15: Severity | D15: Probability | E15: Impact Assessment | F15: Architectural Mitigation Strategy
A16: RSK-01 | B16: QuickBooks Desktop Web Connector concurrency locks or transaction timeouts during simultaneous polling. | C16: High | D16: High | E16: Sync queue blocks or creates partial records in QB. | F16: Implement sequential database queue with atomic lock (sp_getapplock). Store QB TxnID immediately to ensure idempotency.
A17: RSK-02 | B17: Inventory race conditions when multiple office users confirm orders for identical stock simultaneously. | C17: High | D17: Medium | E17: Inventory oversold resulting in unfulfilled customer orders. | F17: Apply EF Core optimistic concurrency ([Timestamp] RowVersion) on Part entity with Serializable database transactions.
A18: RSK-03 | B18: Vendor invoice AI extraction errors on complex or irregular European invoice formats. | C18: Medium | D18: High | E18: Incorrect part matching or erroneous EUR costs saved. | F18: Strict Human-in-the-Loop review: split-screen UI requires manual confirmation before saving to master part or QB Bill queue.
A19: RSK-04 | B19: Vendor cost increases on parts for orders already confirmed with customers. | C19: Medium | D19: High | E19: Profit margin erosion or customer billing disputes. | F19: System recalculates future selling prices but explicitly flags open customer orders for manual review without auto-changing prices.
A20: RSK-05 | B20: UPS Carrier API rate limits or intermittent network outages at shipping docks. | C20: Low | D20: Medium | E20: Warehouse shipping operations temporarily blocked. | F20: Built-in manual override allows warehouse personnel to enter tracking numbers and shipping costs manually.
A21: RSK-06 | B21: QuickBooks company file schema discrepancies between test file and live production company file. | C21: High | D21: Low | E21: QBWC SOAP fails to locate required Chart of Accounts or Items. | F21: Dedicated pre-launch verification script validates all Account Names, Tax Codes, and Item Masters against live QB Desktop prior to cutover.
